vcspull/__about__.py
vcspull/__init__.py
vcspull/config.py
vcspull/exc.py
vcspull/log.py
vcspull/types.py
vcspull/util.py
vcspull/validator.py
vcspull/_internal/__init__.py
vcspull/_internal/config_reader.py
vcspull/_internal/private_path.py
vcspull/cli/__init__.py
vcspull/cli/_colors.py
vcspull/cli/_formatter.py
vcspull/cli/_output.py
vcspull/cli/_workspaces.py
vcspull/cli/add.py
vcspull/cli/discover.py
vcspull/cli/fmt.py
vcspull/cli/list.py
vcspull/cli/search.py
vcspull/cli/status.py
vcspull/cli/sync.py
vcspull-1.51.1.dist-info/METADATA
vcspull-1.51.1.dist-info/WHEEL
vcspull-1.51.1.dist-info/entry_points.txt
vcspull-1.51.1.dist-info/licenses/LICENSE
vcspull-1.51.1.dist-info/RECORD
