Metadata-Version: 2.4
Name: vcspull
Version: 1.51.1
Summary: Manage and sync multiple git, mercurial, and svn repos
Author-email: Tony Narlock <tony@git-pull.com>
License: MIT
License-File: LICENSE
Keywords: fetcher,git,hg,json,manage,manager,mercurial,subversion,svn,sync,updater,vcs,vcspull,yaml
Classifier: Development Status :: 4 - Beta
Classifier: Environment :: Web Environment
Classifier: Intended Audience :: Developers
Classifier: License :: OSI Approved :: MIT License
Classifier: Operating System :: MacOS :: MacOS X
Classifier: Operating System :: POSIX
Classifier: Programming Language :: Python
Classifier: Programming Language :: Python :: 3
Classifier: Programming Language :: Python :: 3.10
Classifier: Programming Language :: Python :: 3.11
Classifier: Programming Language :: Python :: 3.12
Classifier: Programming Language :: Python :: 3.13
Classifier: Programming Language :: Python :: 3.14
Classifier: Topic :: System :: Shells
Classifier: Topic :: Utilities
Requires-Python: <4.0,>=3.10
Requires-Dist: colorama>=0.3.9
Requires-Dist: libvcs~=0.38.6
Requires-Dist: pyyaml>=6.0
